dust3r/__init__.py
dust3r/demo.py
dust3r/image_pairs.py
dust3r/inference.py
dust3r/losses.py
dust3r/model.py
dust3r/optim_factory.py
dust3r/patch_embed.py
dust3r/post_process.py
dust3r/training.py
dust3r/viz.py
dust3r/cloud_opt/__init__.py
dust3r/cloud_opt/base_opt.py
dust3r/cloud_opt/commons.py
dust3r/cloud_opt/init_im_poses.py
dust3r/cloud_opt/modular_optimizer.py
dust3r/cloud_opt/optimizer.py
dust3r/cloud_opt/pair_viewer.py
dust3r/croco/__init__.py
dust3r/croco/demo.py
dust3r/croco/pretrain.py
dust3r/croco/datasets/__init__.py
dust3r/croco/datasets/pairs_dataset.py
dust3r/croco/datasets/transforms.py
dust3r/croco/datasets/habitat_sim/__init__.py
dust3r/croco/datasets/habitat_sim/generate_from_metadata.py
dust3r/croco/datasets/habitat_sim/generate_from_metadata_files.py
dust3r/croco/datasets/habitat_sim/generate_multiview_images.py
dust3r/croco/datasets/habitat_sim/multiview_habitat_sim_generator.py
dust3r/croco/datasets/habitat_sim/pack_metadata_files.py
dust3r/croco/datasets/habitat_sim/paths.py
dust3r/croco/models/__init__.py
dust3r/croco/models/blocks.py
dust3r/croco/models/criterion.py
dust3r/croco/models/croco.py
dust3r/croco/models/croco_downstream.py
dust3r/croco/models/dpt_block.py
dust3r/croco/models/head_downstream.py
dust3r/croco/models/masking.py
dust3r/croco/models/pos_embed.py
dust3r/croco/models/curope/__init__.py
dust3r/croco/models/curope/curope2d.py
dust3r/croco/models/curope/setup.py
dust3r/datasets/__init__.py
dust3r/datasets/arkitscenes.py
dust3r/datasets/blendedmvs.py
dust3r/datasets/co3d.py
dust3r/datasets/habitat.py
dust3r/datasets/megadepth.py
dust3r/datasets/scannetpp.py
dust3r/datasets/staticthings3d.py
dust3r/datasets/waymo.py
dust3r/datasets/wildrgbd.py
dust3r/datasets/base/__init__.py
dust3r/datasets/base/base_stereo_view_dataset.py
dust3r/datasets/base/batched_sampler.py
dust3r/datasets/base/easy_dataset.py
dust3r/datasets/utils/__init__.py
dust3r/datasets/utils/cropping.py
dust3r/datasets/utils/transforms.py
starst3r-0.4.0.dist-info/METADATA
starst3r-0.4.0.dist-info/WHEEL
starst3r-0.4.0.dist-info/top_level.txt
starst3r-0.4.0.dist-info/RECORD
