Metadata-Version: 2.1
Name: starst3r
Version: 0.4.0
Summary: Ultra fast 3D reconstruction and novel view synthesis.
Home-page: https://github.com/phuang1024/Starst3r
Author: Patrick Huang
Author-email: phuang1024@gmail.com
Requires-Dist: gsplat
Requires-Dist: numpy
Requires-Dist: pillow
Requires-Dist: torch
Requires-Dist: torchmetrics
Requires-Dist: torchvision
Requires-Dist: tqdm
Requires-Dist: scikit-learn
Requires-Dist: roma
Requires-Dist: gradio
Requires-Dist: matplotlib
Requires-Dist: opencv-python
Requires-Dist: scipy
Requires-Dist: einops
Requires-Dist: trimesh
Requires-Dist: tensorboard
Requires-Dist: pyglet <2
Requires-Dist: huggingface-hub[torch] >=0.22
